jgp_utils/__init__.py
jgp_utils/date_time.py
jgp_utils/numero_letras.py
jgp_utils/utils.py
jgp_utils-0.0.5.dist-info/LICENSE
jgp_utils-0.0.5.dist-info/METADATA
jgp_utils-0.0.5.dist-info/WHEEL
jgp_utils-0.0.5.dist-info/top_level.txt
jgp_utils-0.0.5.dist-info/RECORD
