Metadata-Version: 2.1
Name: jgp_utils
Version: 0.0.5
Summary: Librería con funciones y herramientas útiles
Home-page: https://gitlab.com/jgp-devs2/jgp-lib/jgp-utils
Author: Sistemas
Author-email: sistemas@jesusgranpoder.com.bo
License: MIT
License-File: LICENSE
